ours_privacy/__init__.py
ours_privacy/_base_client.py
ours_privacy/_client.py
ours_privacy/_compat.py
ours_privacy/_constants.py
ours_privacy/_exceptions.py
ours_privacy/_files.py
ours_privacy/_models.py
ours_privacy/_qs.py
ours_privacy/_resource.py
ours_privacy/_response.py
ours_privacy/_streaming.py
ours_privacy/_types.py
ours_privacy/_version.py
ours_privacy/py.typed
ours_privacy/_utils/__init__.py
ours_privacy/_utils/_compat.py
ours_privacy/_utils/_datetime_parse.py
ours_privacy/_utils/_json.py
ours_privacy/_utils/_logs.py
ours_privacy/_utils/_proxy.py
ours_privacy/_utils/_reflection.py
ours_privacy/_utils/_resources_proxy.py
ours_privacy/_utils/_streams.py
ours_privacy/_utils/_sync.py
ours_privacy/_utils/_transform.py
ours_privacy/_utils/_typing.py
ours_privacy/_utils/_utils.py
ours_privacy/lib/.keep
ours_privacy/resources/__init__.py
ours_privacy/resources/track.py
ours_privacy/resources/visitor.py
ours_privacy/types/__init__.py
ours_privacy/types/track_event_params.py
ours_privacy/types/track_event_response.py
ours_privacy/types/visitor_upsert_params.py
ours_privacy/types/visitor_upsert_response.py
oursprivacy_client-1.8.0.dist-info/METADATA
oursprivacy_client-1.8.0.dist-info/WHEEL
oursprivacy_client-1.8.0.dist-info/licenses/LICENSE
oursprivacy_client-1.8.0.dist-info/RECORD
